mgclient.cpython-311-darwin.so
pymgclient-1.5.1.dist-info/licenses/LICENSE
pymgclient-1.5.1.dist-info/METADATA
pymgclient-1.5.1.dist-info/WHEEL
pymgclient-1.5.1.dist-info/top_level.txt
pymgclient-1.5.1.dist-info/RECORD
